utk_exodus/__init__.py
utk_exodus/banish/__init__.py
utk_exodus/banish/banish.py
utk_exodus/checksum/__init__.py
utk_exodus/checksum/checksum.py
utk_exodus/collection/__init__.py
utk_exodus/collection/collection.py
utk_exodus/combine/__init__.py
utk_exodus/combine/combine.py
utk_exodus/config/samvera_default.yml
utk_exodus/config/utk_dc.yml
utk_exodus/config/utk_dc_no_uris.yml
utk_exodus/config/utk_no_uris_no_names.yml
utk_exodus/controller/__init__.py
utk_exodus/controller/controller.py
utk_exodus/curate/__init__.py
utk_exodus/curate/curate.py
utk_exodus/exodus.py
utk_exodus/fedora/__init__.py
utk_exodus/fedora/fedora.py
utk_exodus/finder/__init__.py
utk_exodus/finder/finder.py
utk_exodus/fixes/__init__.py
utk_exodus/fixes/fixes.py
utk_exodus/metadata/__init__.py
utk_exodus/metadata/base/__init__.py
utk_exodus/metadata/base/base.py
utk_exodus/metadata/metadata.py
utk_exodus/restrict/__init__.py
utk_exodus/restrict/restrict.py
utk_exodus/review/__init__.py
utk_exodus/review/review.py
utk_exodus/risearch/__init__.py
utk_exodus/risearch/risearch.py
utk_exodus/template/__init__.py
utk_exodus/template/template.py
utk_exodus/validate/__init__.py
utk_exodus/validate/validate.py
utk_exodus-0.2.13.dist-info/METADATA
utk_exodus-0.2.13.dist-info/WHEEL
utk_exodus-0.2.13.dist-info/entry_points.txt
utk_exodus-0.2.13.dist-info/RECORD
