Metadata-Version: 2.3
Name: utk-exodus
Version: 0.2.13
Summary: A tool for building import sheets from UTK legacy systems
Author: Mark Baggett
Author-email: mbagget1@utk.edu
Requires-Python: >=3.8,<4.0
Classifier: Programming Language :: Python :: 3
Classifier: Programming Language :: Python :: 3.8
Classifier: Programming Language :: Python :: 3.9
Classifier: Programming Language :: Python :: 3.10
Classifier: Programming Language :: Python :: 3.11
Classifier: Programming Language :: Python :: 3.12
Classifier: Programming Language :: Python :: 3.13
Requires-Dist: black (>=24.4.2,<25.0.0)
Requires-Dist: click (>=8.1.7,<9.0.0)
Requires-Dist: lxml (>=5.2.1,<6.0.0)
Requires-Dist: pytest (>=8.2.0,<9.0.0)
Requires-Dist: pyyaml (>=6.0.1,<7.0.0)
Requires-Dist: requestium (>=0.4.0,<0.5.0)
Requires-Dist: requests (>=2.31.0,<3.0.0)
Requires-Dist: ruff (>=0.4.2,<0.5.0)
Requires-Dist: selenium (>=4.21.0,<5.0.0)
Requires-Dist: selenium-requests (>=2.0.4,<3.0.0)
Requires-Dist: tqdm (>=4.66.2,<5.0.0)
Requires-Dist: xmltodict (>=0.13.0,<0.14.0)
